CHANGELOG.txt
LICENSE.txt
MANIFEST.in
README.txt
setup.py
DEfitnessFunction/__init__.py
FitnessFunction.egg-info/PKG-INFO
FitnessFunction.egg-info/SOURCES.txt
FitnessFunction.egg-info/dependency_links.txt
FitnessFunction.egg-info/top_level.txt