Metadata-Version: 1.1
Name: FitnessFunction
Version: 0.0.1
Summary: this library is besically for fitness function of DE
Home-page: https://github.com/pawanmishra0532/Fitness_Function
Author: Pawan Mishra
Author-email: pawanmishra0532@gmail.com
License: MIT
Keywords: Differential Evolution,Fitness function Code,Cost_function_library
Platform: UNKNOWN
Classifier: Development Status :: 5 - Production/Stable
Classifier: Intended Audience :: Education
Classifier: Operating System :: Microsoft :: Windows :: Windows 10
Classifier: License :: OSI Approved :: MIT License
Classifier: Programming Language :: Python :: 3
